quorum/__init__.py
quorum/__main__.py
quorum/agents.py
quorum/config.py
quorum/constants.py
quorum/ipc.py
quorum/main.py
quorum/models.py
quorum/providers.py
quorum/team.py
quorum/clients/__init__.py
quorum/clients/anthropic_client.py
quorum/clients/openai_client.py
quorum/clients/types.py
quorum/mcp/__init__.py
quorum/methods/__init__.py
quorum/methods/advocate.py
quorum/methods/base.py
quorum/methods/brainstorm.py
quorum/methods/delphi.py
quorum/methods/oxford.py
quorum/methods/socratic.py
quorum/methods/standard.py
quorum/methods/tradeoff.py
quorum/.env.example
quorum/_frontend/App.d.ts
quorum/_frontend/App.js
quorum/_frontend/index.d.ts
quorum/_frontend/index.js
quorum/_frontend/components/CommandPalette.d.ts
quorum/_frontend/components/CommandPalette.js
quorum/_frontend/components/Discussion.d.ts
quorum/_frontend/components/Discussion.js
quorum/_frontend/components/ExportSelector.d.ts
quorum/_frontend/components/ExportSelector.js
quorum/_frontend/components/Header.d.ts
quorum/_frontend/components/Header.js
quorum/_frontend/components/Help.d.ts
quorum/_frontend/components/Help.js
quorum/_frontend/components/Input.d.ts
quorum/_frontend/components/Input.js
quorum/_frontend/components/LanguageSelector.d.ts
quorum/_frontend/components/LanguageSelector.js
quorum/_frontend/components/Message.d.ts
quorum/_frontend/components/Message.js
quorum/_frontend/components/MethodAdvisor.d.ts
quorum/_frontend/components/MethodAdvisor.js
quorum/_frontend/components/MethodSelector.d.ts
quorum/_frontend/components/MethodSelector.js
quorum/_frontend/components/ModelSelector.d.ts
quorum/_frontend/components/ModelSelector.js
quorum/_frontend/components/Status.d.ts
quorum/_frontend/components/Status.js
quorum/_frontend/components/SynthesizerSelector.d.ts
quorum/_frontend/components/SynthesizerSelector.js
quorum/_frontend/components/TeamPreview.d.ts
quorum/_frontend/components/TeamPreview.js
quorum/_frontend/components/index.d.ts
quorum/_frontend/components/index.js
quorum_cli-1.1.5.dist-info/METADATA
quorum_cli-1.1.5.dist-info/WHEEL
quorum_cli-1.1.5.dist-info/entry_points.txt
quorum_cli-1.1.5.dist-info/licenses/LICENSE
quorum_cli-1.1.5.dist-info/RECORD
