Metadata-Version: 2.4
Name: quorum-cli
Version: 1.1.5
Summary: Multi-agent AI discussion system for structured debates
Project-URL: Homepage, https://github.com/Detrol/quorum-cli
Project-URL: Repository, https://github.com/Detrol/quorum-cli
Project-URL: Issues, https://github.com/Detrol/quorum-cli/issues
Author-email: Detrol <andreas.thun@gmail.com>
License: BSL-1.1
License-File: LICENSE
Keywords: ai,brainstorm,consensus,debate,deliberation,discussion,llm,multi-agent
Classifier: Development Status :: 5 - Production/Stable
Classifier: Environment :: Console
Classifier: Intended Audience :: Developers
Classifier: License :: Other/Proprietary License
Classifier: Operating System :: OS Independent
Classifier: Programming Language :: Python :: 3
Classifier: Programming Language :: Python :: 3.11
Classifier: Programming Language :: Python :: 3.12
Classifier: Topic :: Scientific/Engineering :: Artificial Intelligence
Requires-Python: >=3.11
Requires-Dist: anthropic<1.0,>=0.40
Requires-Dist: google-genai<2.0,>=1.0
Requires-Dist: httpx<1.0,>=0.24
Requires-Dist: mcp>=1.0.0
Requires-Dist: openai<2.0,>=1.0
Requires-Dist: pydantic-settings<3.0,>=2.0
Requires-Dist: pydantic<3.0,>=2.0
Requires-Dist: python-dotenv<2.0,>=1.0
Provides-Extra: test
Requires-Dist: pytest-asyncio<1.0,>=0.24; extra == 'test'
Requires-Dist: pytest-cov<6.0,>=5.0; extra == 'test'
Requires-Dist: pytest-ruff<1.0,>=0.4.0; extra == 'test'
Requires-Dist: pytest-timeout<3.0,>=2.0; extra == 'test'
Requires-Dist: pytest<9.0,>=8.0; extra == 'test'
Requires-Dist: ruff<1.0,>=0.1.0; extra == 'test'
